upersetter/__init__.py
upersetter/handler.py
upersetter/make.py
upersetter/scan.py
upersetter/upersetter.py
upersetter/utils.py
upersetter-0.8.6.dist-info/DESCRIPTION.rst
upersetter-0.8.6.dist-info/METADATA
upersetter-0.8.6.dist-info/RECORD
upersetter-0.8.6.dist-info/WHEEL
upersetter-0.8.6.dist-info/metadata.json
upersetter-0.8.6.dist-info/top_level.txt
