Metadata-Version: 2.0
Name: upersetter
Version: 0.8.6
Summary: upersetter helps with automating basic setup tasks for any kind of project in a general way.
Home-page: https://github.com/vaubarth/upersetter
Author: Vincent Barth
Author-email: vdbarth@posteo.at
License: Mozilla Public License 2.0 (MPL 2.0)
Platform: UNKNOWN
Classifier: Programming Language :: Python :: 3 :: Only
Classifier: Programming Language :: Python :: 3.6
Classifier: License :: OSI Approved :: Mozilla Public License 2.0 (MPL 2.0)
Requires-Dist: jinja2
Requires-Dist: pyyaml
Requires-Dist: dpath
Requires-Dist: click
Requires-Dist: anypath
